dativa/tools/__init__.py
dativa/tools/file_validation.py
dativa/tools/aws/__init__.py
dativa/tools/aws/athena.py
dativa/tools/aws/dynamodb.py
dativa/tools/aws/pipeline_client.py
dativa/tools/aws/s3_lib.py
dativa/tools/aws/s3csv2parquet.py
dativa/tools/aws/task_queue.py
dativa/tools/aws/template_scripts/csv_parquet_template.py
dativa/tools/db/__init__.py
dativa/tools/db/sql_client.py
dativa/tools/logging/__init__.py
dativa/tools/logging/logger.py
dativa/tools/pandas/__init__.py
dativa/tools/pandas/athena_partition.py
dativa/tools/pandas/attribution_tools.py
dativa/tools/pandas/columns.py
dativa/tools/pandas/csv.py
dativa/tools/pandas/date_time.py
dativa/tools/pandas/ipf.py
dativa/tools/pandas/parquet_handler.py
dativa/tools/tests/__init__.py
dativa/tools/tests/test_athena.py
dativa/tools/tests/test_attribution.py
dativa/tools/tests/test_csv.py
dativa/tools/tests/test_dynamodb.py
dativa/tools/tests/test_file_validation.py
dativa/tools/tests/test_ipf.py
dativa/tools/tests/test_parquet_handler.py
dativa/tools/tests/test_partition.py
dativa/tools/tests/test_python_client_pipeline_api.py
dativa/tools/tests/test_s3.py
dativa/tools/tests/test_s3csv2parquet.py
dativa/tools/tests/test_sql.py
dativa/tools/tests/test_data/demographic_data_op.csv
dativa/tools/tests/test_data/athena_partition/expected_csv.csv
dativa/tools/tests/test_data/athena_partition/expected_multi_csv.csv
dativa/tools/tests/test_data/athena_partition/expected_parquet.parquet
dativa/tools/tests/test_data/attribution/conversions.csv
dativa/tools/tests/test_data/attribution/conversions_to_filter.csv
dativa/tools/tests/test_data/attribution/impressions.csv
dativa/tools/tests/test_data/attribution/impressions_to_filter.csv
dativa/tools/tests/test_data/attribution/rd_cids_conversion.csv
dativa/tools/tests/test_data/attribution/scored_conversions.csv
dativa/tools/tests/test_data/attribution/scored_impressions.csv
dativa/tools/tests/test_data/csvhandler/anonymization/email_list.csv
dativatools-3.0.371.dist-info/METADATA
dativatools-3.0.371.dist-info/WHEEL
dativatools-3.0.371.dist-info/top_level.txt
dativatools-3.0.371.dist-info/RECORD
