Metadata-Version: 2.1
Name: dativatools
Version: 3.0.371
Summary: A selection of tools for easier processing of data using Pandas and AWS
Home-page: https://bitbucket.org/dativa4data/dativatools/
Author: Dativa
Author-email: hello@dativa.com
License: MIT
Keywords: dativa
Platform: UNKNOWN
Classifier: Development Status :: 5 - Production/Stable
Classifier: Intended Audience :: Developers
Classifier: Topic :: Software Development :: Libraries
Classifier: License :: OSI Approved :: MIT License
Classifier: Programming Language :: Python :: 3.6
